dbxnotebookexporter/databricks/databricks_notebook.tpl
dbxnotebookexporter/databricks/DatabricksNotebookExporter.py
dbxnotebookexporter/json/formatCellContent.py
dbxnotebookexporter/json/json_notebook.tpl
dbxnotebookexporter/json/JsonNotebookExporter.py
dbxnotebookexporter/python/python_notebook.tpl
dbxnotebookexporter/python/PythonNotebookExporter.py
dbx_notebook_exporter-0.4.1.dist-info/entry_points.txt
dbx_notebook_exporter-0.4.1.dist-info/LICENSE.md
dbx_notebook_exporter-0.4.1.dist-info/WHEEL
dbx_notebook_exporter-0.4.1.dist-info/METADATA
dbx_notebook_exporter-0.4.1.dist-info/RECORD
