Metadata-Version: 2.1
Name: dbx-notebook-exporter
Version: 0.4.1
Summary: Databrics Notebook Exporter
Home-page: https://github.com/bricksflow/dbx-notebook-exporter
License: MIT
Author: Jiri Koutny
Author-email: jiri.koutny@datasentics.com
Requires-Python: >=3.5.2
Classifier: License :: OSI Approved :: MIT License
Classifier: Operating System :: OS Independent
Classifier: Programming Language :: Python :: 3
Classifier: Programming Language :: Python :: 3.6
Classifier: Programming Language :: Python :: 3.7
Classifier: Programming Language :: Python :: 3.8
Classifier: Programming Language :: Python :: 3.9
Requires-Dist: ipython (>=7.8)
Requires-Dist: nbconvert (>=5.6)
Project-URL: Repository, https://github.com/bricksflow/dbx-notebook-exporter
